llmapi_cli/__init__.py
llmapi_cli/llmclient.py
llmapi_cli-1.1.1.dist-info/LICENSE
llmapi_cli-1.1.1.dist-info/METADATA
llmapi_cli-1.1.1.dist-info/WHEEL
llmapi_cli-1.1.1.dist-info/entry_points.txt
llmapi_cli-1.1.1.dist-info/top_level.txt
llmapi_cli-1.1.1.dist-info/RECORD
